{
  "android_apns": [
    {
      "apn": "a2bouygtel.com",
      "name": "Contrat Pro Data Illimit\u00e9",
      "types": [
        "default",
        "supl"
      ]
    },
    {
      "apn": "b2bouygtel.com",
      "name": "B2Bouygtel",
      "types": [
        "default",
        "supl"
      ]
    },
    {
      "apn": "ebouygtel.com",
      "name": "Forfait Data",
      "types": [
        "default",
        "supl"
      ]
    },
    {
      "apn": "mmsbouygtel.com",
      "name": "Forfait Data",
      "types": [
        "default",
        "supl"
      ]
    },
    {
      "apn": "mmsbouygtel.com",
      "mmsc": "http://mms.bouyguestelecom.fr/mms/wapenc",
      "mmsport": 8080,
      "mmsproxy": "62.201.129.226",
      "name": "Bouygues MMS",
      "types": [
        "mms"
      ]
    },
    {
      "apn": "pcebouygtel.com",
      "name": "Contrat Pro Data",
      "types": [
        "default",
        "supl"
      ]
    }
  ],
  "capabilities": {
    "esim": "unknown",
    "ims_conference": "unknown",
    "mms": "supported",
    "rcs": "unknown",
    "sms_over_ims": "unknown",
    "video_calling": "unknown",
    "volte": "unknown",
    "vonr": "unknown",
    "vowifi": "unknown",
    "wifi_calling_roaming": "unknown"
  },
  "display_name": "Bouygues Telecom",
  "match": {
    "mccmnc": [
      "20820",
      "20821"
    ]
  },
  "profile_id": "open.20820.27d00b6edaef",
  "schema_version": 1
}
