{
  "android_apns": [
    {
      "apn": "altecom.net",
      "name": "Altecom Es",
      "types": [
        "default"
      ]
    },
    {
      "apn": "altecom.net",
      "carrier_id": 2131,
      "name": "ALTECOM",
      "types": [
        "default",
        "ia"
      ]
    },
    {
      "apn": "movistar.es",
      "name": "Movistar",
      "password": "MOVISTAR",
      "types": [
        "default",
        "dun"
      ],
      "user": "MOVISTAR"
    },
    {
      "apn": "telefonica.es",
      "name": "Movistar",
      "password": "telefonica",
      "port": 8080,
      "proxy": "10.138.255.133",
      "types": [
        "default",
        "supl"
      ],
      "user": "telefonica"
    },
    {
      "apn": "telefonica.es",
      "mmsc": "http://mms.movistar.com",
      "mmsport": 8080,
      "mmsproxy": "10.138.255.5",
      "name": "Movistar MMS",
      "password": "telefonica",
      "types": [
        "mms"
      ],
      "user": "telefonica"
    },
    {
      "apn": "fibracat.cat",
      "carrier_id": 2136,
      "mvno_match_data": "FIBRACAT",
      "mvno_type": "spn",
      "name": "FIBRACAT",
      "types": [
        "default",
        "ia"
      ]
    }
  ],
  "android_carrier_config": {
    "maxMessageSize": 512000
  },
  "capabilities": {
    "esim": "unknown",
    "ims_conference": "unknown",
    "mms": "supported",
    "rcs": "unknown",
    "sms_over_ims": "unknown",
    "video_calling": "unknown",
    "volte": "unknown",
    "vonr": "unknown",
    "vowifi": "unknown",
    "wifi_calling_roaming": "unknown"
  },
  "display_name": "Carrier 21402",
  "match": {
    "mccmnc": [
      "21402"
    ]
  },
  "profile_id": "open.21402.570ff677b114",
  "schema_version": 1
}
