{
  "addons": {
    "emergency_calling": {
      "e911_routing_policy": "auto",
      "emergency_dial_call_style": "EndPreviousCall"
    },
    "ims": {
      "support_ims_clir_overriding": true
    },
    "network_policy": {
      "display_antenna_limited": true,
      "gcf_sor": true,
      "network_selection_menu_style": "NUMERIC",
      "network_type_capability": "EUR-EUR-GSM-EUR",
      "voice_network_setting_style": "SupportDualDataRoam"
    },
    "operator_display": {
      "five_g_icon_configuration": [
        "connected_mmwave:5G",
        "connected:5G",
        "not_restricted_rrc_idle:5G",
        "not_restricted_rrc_con:5G"
      ],
      "refer_eons_without_lac": true
    }
  },
  "android_apns": [
    {
      "apn": "internet.telecable.es",
      "authtype": 1,
      "carrier_enabled": true,
      "name": "internet.telecable.es",
      "password": "telecable",
      "types": [
        "default",
        "supl"
      ],
      "user": "telecable"
    },
    {
      "apn": "internet.telecable.es",
      "name": "TeleCable Internet",
      "password": "telecable",
      "types": [
        "ia"
      ],
      "user": "telecable"
    },
    {
      "apn": "mms.telecable.es",
      "authtype": 1,
      "carrier_enabled": true,
      "mmsc": "http://mms.telecable.es/mms/",
      "mmsport": 8080,
      "mmsproxy": "212.89.0.84",
      "name": "mms.telecable.es",
      "password": "telecable",
      "types": [
        "mms"
      ],
      "user": "telecable"
    },
    {
      "apn": "internet.telecable.es",
      "authtype": 1,
      "mvno_match_data": "telecable",
      "mvno_type": "spn",
      "name": "telecable Internet",
      "password": "telecable",
      "types": [
        "default",
        "supl"
      ],
      "user": "telecable"
    },
    {
      "apn": "mms.telecable.es",
      "authtype": 1,
      "mmsc": "http://mms.telecable.es/mms/",
      "mmsport": 8080,
      "mmsproxy": "212.89.0.84",
      "mvno_match_data": "telecable",
      "mvno_type": "spn",
      "name": "telecable MMS",
      "password": "telecable",
      "types": [
        "mms"
      ],
      "user": "telecable"
    }
  ],
  "android_carrier_config": {
    "carrier_metered_apn_types_strings": [
      "default",
      "dun",
      "mms",
      "supl"
    ],
    "carrier_volte_available_bool": true,
    "enabledMMS": false
  },
  "capabilities": {
    "esim": "unknown",
    "ims_conference": "unknown",
    "mms": "conditional",
    "rcs": "unknown",
    "sms_over_ims": "unknown",
    "video_calling": "unknown",
    "volte": "supported",
    "vonr": "unknown",
    "vowifi": "unknown",
    "wifi_calling_roaming": "unknown"
  },
  "display_name": "Carrier 21416",
  "match": {
    "mccmnc": [
      "21416"
    ]
  },
  "profile_id": "open.21416.4b4a1d23619c",
  "schema_version": 1
}
