{
  "android_apns": [
    {
      "apn": "mms.iusacellgsm.mx",
      "authtype": 0,
      "mmsc": "http://mms.iusacell3g.com/",
      "name": "MMS",
      "password": "mmsiusacellgsm",
      "types": [
        "mms"
      ],
      "user": "mmsiusacellgsm"
    },
    {
      "apn": "modem.iusacellgsm.mx",
      "authtype": 0,
      "name": "Modem",
      "password": "iusacellgsm",
      "types": [
        "dun"
      ],
      "user": "iusacellgsm",
      "user_editable": false
    },
    {
      "apn": "web.iusacellgsm.mx",
      "authtype": 0,
      "name": "Internet",
      "password": "iusacellgsm",
      "types": [
        "default"
      ],
      "user": "iusacellgsm"
    }
  ],
  "android_carrier_config": {
    "maxImageHeight": 1944,
    "maxImageWidth": 2592,
    "maxMessageSize": 1048576
  },
  "capabilities": {
    "esim": "unknown",
    "ims_conference": "unknown",
    "mms": "supported",
    "rcs": "unknown",
    "sms_over_ims": "unknown",
    "video_calling": "unknown",
    "volte": "unknown",
    "vonr": "unknown",
    "vowifi": "unknown",
    "wifi_calling_roaming": "unknown"
  },
  "display_name": "22201Spn=Iusacell",
  "match": {
    "mccmnc": [
      "22201"
    ],
    "spn": [
      "IUSACELL"
    ]
  },
  "profile_id": "open.22201.4411b77325c6",
  "schema_version": 1
}
