{
  "android_apns": [
    {
      "apn": "mobile.erg.it",
      "authtype": 0,
      "name": "ErgMobile WAP",
      "types": [
        "default",
        "dun",
        "fota",
        "supl"
      ],
      "user_editable": false
    }
  ],
  "android_carrier_config": {
    "carrier_volte_available_bool": false,
    "volte_replacement_rat_int": 3
  },
  "capabilities": {
    "esim": "unknown",
    "ims_conference": "unknown",
    "mms": "unknown",
    "rcs": "unknown",
    "sms_over_ims": "unknown",
    "video_calling": "unknown",
    "volte": "unsupported",
    "vonr": "unknown",
    "vowifi": "unknown",
    "wifi_calling_roaming": "unknown"
  },
  "display_name": "22210Spn=Erg",
  "match": {
    "mccmnc": [
      "22210"
    ],
    "spn": [
      "ERG"
    ]
  },
  "profile_id": "open.22210.0ca339e71d8c",
  "schema_version": 1
}
