{
  "android_apns": [
    {
      "apn": "internet",
      "carrier_id": 1491,
      "name": "UBIQUISYS",
      "types": [
        "default",
        "ia",
        "supl"
      ]
    },
    {
      "apn": "internet",
      "name": "UBIQUISYS",
      "types": [
        "default",
        "supl"
      ]
    },
    {
      "apn": "prepay.tesco-mobile.com",
      "name": "Tesco Prepay",
      "password": "password",
      "port": 9201,
      "proxy": "193.113.200.195",
      "server": "http://wap.tesco-mobile.com/",
      "types": [
        "default",
        "mms",
        "supl"
      ],
      "user": "tescowap"
    },
    {
      "apn": "webuk.mundio.com",
      "name": "Vectone Mobile",
      "types": [
        "default",
        "supl"
      ]
    },
    {
      "apn": "internet",
      "mvno_match_data": "Vectone Mobile",
      "mvno_type": "spn",
      "name": "UBIQUISYS",
      "types": [
        "default",
        "mms",
        "supl"
      ]
    }
  ],
  "capabilities": {
    "esim": "unknown",
    "ims_conference": "unknown",
    "mms": "supported",
    "rcs": "unknown",
    "sms_over_ims": "unknown",
    "video_calling": "unknown",
    "volte": "unknown",
    "vonr": "unknown",
    "vowifi": "unknown",
    "wifi_calling_roaming": "unknown"
  },
  "display_name": "Carrier 23401",
  "match": {
    "mccmnc": [
      "23401"
    ]
  },
  "profile_id": "open.23401.6c780abba051",
  "schema_version": 1
}
