{
  "android_apns": [
    {
      "apn": "internet.tele2.ee",
      "mmsc": "http://mmsc.tele2.ee",
      "mmsport": 8080,
      "mmsproxy": "mmsproxy.tele2.ee",
      "name": "internet.tele2.ee",
      "password": "wap",
      "types": [
        "default"
      ],
      "user": "wap"
    },
    {
      "apn": "internet.tele2.ee",
      "name": "internet.tele2.ee",
      "password": "wap",
      "types": [
        "supl"
      ],
      "user": "wap"
    },
    {
      "apn": "mms.emt.ee",
      "mmsc": "http://mms.emt.ee/servlets/mms",
      "mmsport": 8080,
      "mmsproxy": "217.71.32.82",
      "name": "Tele2 EE MMS",
      "types": [
        "mms"
      ]
    }
  ],
  "android_carrier_config": {
    "carrier_volte_available_bool": true,
    "carrier_vt_available_bool": true,
    "carrier_wfc_ims_available_bool": true,
    "imssms.sms_over_ims_supported_bool": true
  },
  "capabilities": {
    "esim": "unknown",
    "ims_conference": "unknown",
    "mms": "supported",
    "rcs": "unknown",
    "sms_over_ims": "supported",
    "video_calling": "supported",
    "volte": "supported",
    "vonr": "unknown",
    "vowifi": "supported",
    "wifi_calling_roaming": "unknown"
  },
  "display_name": "Carrier 24803",
  "match": {
    "mccmnc": [
      "24803"
    ]
  },
  "profile_id": "open.24803.3a0f48326f77",
  "schema_version": 1
}
