{
  "android_apns": [
    {
      "apn": "ims",
      "name": "TELUS",
      "protocol": "IPV6",
      "roaming_protocol": "IPV6",
      "types": [
        "ims"
      ]
    },
    {
      "apn": "inet.clearnet.com",
      "mmsc": "http://aliasredirect.net/proxy/clearnet/mmsc",
      "mmsport": 80,
      "mmsproxy": "74.49.0.18",
      "name": "Clearnet",
      "port": 80,
      "proxy": "74.49.0.18",
      "types": [
        "default",
        "mms",
        "supl"
      ]
    },
    {
      "apn": "isp.telus.com",
      "mmsc": "http://aliasredirect.net/proxy/mmsc",
      "mmsport": 80,
      "mmsproxy": "74.49.0.18",
      "name": "isp.telus.com",
      "types": [
        "default",
        "mms",
        "supl"
      ]
    },
    {
      "apn": "isp.telus.com",
      "name": "TELUS",
      "types": [
        "dun"
      ]
    },
    {
      "apn": "sos",
      "name": "TELUS",
      "protocol": "IPV6",
      "roaming_protocol": "IPV6",
      "types": [
        "emergency"
      ]
    },
    {
      "apn": "sp.koodo.com",
      "mmsc": "http://aliasredirect.net/proxy/koodo/mmsc",
      "mmsport": 80,
      "mmsproxy": "74.49.0.18",
      "name": "sp.koodo.com",
      "port": 80,
      "proxy": "74.49.0.18",
      "types": [
        "default",
        "mms",
        "supl"
      ]
    },
    {
      "apn": "sp.mb.com",
      "mmsc": "http://aliasredirect.net/proxy/mb/mmsc",
      "mmsport": 80,
      "mmsproxy": "74.49.0.18",
      "name": "sp.mb.com",
      "types": [
        "default",
        "mms",
        "supl"
      ]
    },
    {
      "apn": "sp.telus.com",
      "mmsc": "http://aliasredirect.net/proxy/mmsc",
      "mmsport": 80,
      "mmsproxy": "74.49.0.18",
      "name": "sp.telus.com",
      "protocol": "IP",
      "roaming_protocol": "IP",
      "types": [
        "default"
      ]
    },
    {
      "apn": "sp.telus.com",
      "mmsc": "http://aliasredirect.net/proxy/mmsc",
      "mmsport": 80,
      "mmsproxy": "74.49.0.18",
      "name": "sp.telus.com",
      "types": [
        "supl"
      ]
    },
    {
      "apn": "ims",
      "bearer_bitmask": "3|9|10|11|14|15|18|20",
      "carrier_id": 2020,
      "mvno_match_data": "4B4F",
      "mvno_type": "gid",
      "name": "Koodo IMS",
      "protocol": "IPV6",
      "roaming_protocol": "IPV6",
      "types": [
        "ims"
      ],
      "user_visible": false
    },
    {
      "apn": "services.koodo.com",
      "bearer_bitmask": "18",
      "carrier_id": 2020,
      "mmsc": "http://aliasredirect.net/proxy/koodo/mmsc",
      "mmsport": 8799,
      "mmsproxy": "mmscproxy.mobility.ca",
      "mvno_match_data": "4B4F",
      "mvno_type": "gid",
      "name": "Koodo Services",
      "protocol": "IPV6",
      "roaming_protocol": "IPV4V6",
      "types": [
        "mms",
        "xcap"
      ],
      "user_editable": false
    },
    {
      "apn": "services.koodo.com",
      "bearer_bitmask": "1|2|3|9|10|11|13|14|15|20",
      "carrier_id": 2020,
      "mvno_match_data": "4B4F",
      "mvno_type": "gid",
      "name": "Koodo Services",
      "protocol": "IPV6",
      "roaming_protocol": "IPV4V6",
      "types": [
        "xcap"
      ],
      "user_visible": false
    },
    {
      "apn": "services.koodo.com",
      "authtype": 0,
      "mtu": 1440,
      "mvno_match_data": "4B4F",
      "mvno_type": "gid",
      "name": "Koodo Services",
      "protocol": "IPV6",
      "roaming_protocol": "IPV4V6",
      "types": [
        "xcap"
      ]
    },
    {
      "apn": "sos",
      "carrier_id": 2020,
      "mvno_match_data": "4B4F",
      "mvno_type": "gid",
      "name": "Koodo SOS",
      "protocol": "IPV6",
      "roaming_protocol": "IPV4V6",
      "types": [
        "emergency"
      ],
      "user_visible": false
    },
    {
      "apn": "sos",
      "authtype": 0,
      "mvno_match_data": "4B4F",
      "mvno_type": "gid",
      "name": "SOS",
      "protocol": "IPV6",
      "roaming_protocol": "IPV4V6",
      "types": [
        "emergency"
      ]
    },
    {
      "apn": "sp.koodo.com",
      "bearer_bitmask": "1|2|3|4|5|6|7|8|9|10|11|12|13|14|15|17|20",
      "carrier_id": 2020,
      "mmsc": "http://aliasredirect.net/proxy/koodo/mmsc",
      "mmsport": 8799,
      "mmsproxy": "mmscproxy.mobility.ca",
      "mvno_match_data": "4B4F",
      "mvno_type": "gid",
      "name": "Koodo",
      "protocol": "IPV4V6",
      "types": [
        "default",
        "dun",
        "ia",
        "mms"
      ],
      "user_editable": false
    },
    {
      "apn": "sp.koodo.com",
      "authtype": 0,
      "mmsc": "http://aliasredirect.net/proxy/koodo/mmsc",
      "mmsport": 8799,
      "mmsproxy": "mmscproxy.mobility.ca",
      "mvno_match_data": "4B4F",
      "mvno_type": "gid",
      "name": "Koodo SP",
      "types": [
        "default",
        "dun",
        "mms",
        "supl"
      ]
    },
    {
      "apn": "sp.koodo.com",
      "carrier_id": 2020,
      "mmsc": "http://aliasredirect.net/proxy/koodo/mmsc",
      "mmsport": 8799,
      "mmsproxy": "mmscproxy.mobility.ca",
      "mvno_match_data": "4B4F",
      "mvno_type": "gid",
      "name": "Koodo",
      "types": [
        "default",
        "ia",
        "mms",
        "supl"
      ]
    },
    {
      "apn": "sp.koodo.com",
      "carrier_id": 2020,
      "mvno_match_data": "4B4F",
      "mvno_type": "gid",
      "name": "Koodo Tether",
      "protocol": "IP",
      "server": "*",
      "types": [
        "dun"
      ]
    },
    {
      "apn": "ccp-services.telus.com",
      "bearer_bitmask": "1|2|3|4|5|6|7|8|9|10|11|12|13|14|15|17|20",
      "mvno_match_data": "4C4F",
      "mvno_type": "gid",
      "name": "TELUS CCP XCAP",
      "protocol": "IPV6",
      "roaming_protocol": "IPV6",
      "types": [
        "xcap"
      ],
      "user_editable": false
    },
    {
      "apn": "ims",
      "bearer_bitmask": "3|9|10|11|14|15|18|20",
      "mvno_match_data": "4C4F",
      "mvno_type": "gid",
      "name": "TELUS IMS",
      "protocol": "IPV6",
      "roaming_protocol": "IPV6",
      "types": [
        "ims"
      ],
      "user_visible": false
    },
    {
      "apn": "isp.telus.com",
      "mvno_match_data": "4C4F",
      "mvno_type": "gid",
      "name": "Telus Tethered",
      "protocol": "IPV4V6",
      "roaming_protocol": "IPV4V6",
      "types": [
        "dun"
      ],
      "user_editable": false
    },
    {
      "apn": "pp.telus.com",
      "bearer_bitmask": "1|2|3|4|5|6|7|8|9|10|11|12|13|14|15|17|20",
      "mvno_match_data": "4C4F",
      "mvno_type": "gid",
      "name": "TELUS CCP",
      "protocol": "IPV4V6",
      "roaming_protocol": "IPV4V6",
      "types": [
        "default",
        "hipri",
        "ia",
        "supl"
      ],
      "user_editable": false
    },
    {
      "apn": "sos",
      "mvno_match_data": "4C4F",
      "mvno_type": "gid",
      "name": "TELUS SOS",
      "protocol": "IPV6",
      "roaming_protocol": "IPV6",
      "types": [
        "emergency"
      ],
      "user_visible": false
    },
    {
      "apn": "sp.telus.com",
      "bearer_bitmask": "1|2|3|4|5|6|7|8|9|10|11|12|13|14|15|17|18|20",
      "mmsc": "http://aliasredirect.net/proxy/mmsc",
      "mmsport": 8799,
      "mmsproxy": "mmscproxy.mobility.ca",
      "mvno_match_data": "4C4F",
      "mvno_type": "gid",
      "name": "TELUS MMS",
      "protocol": "IPV4V6",
      "roaming_protocol": "IPV4V6",
      "types": [
        "mms"
      ],
      "user_editable": false
    },
    {
      "apn": "ims",
      "bearer_bitmask": "3|9|10|11|14|15|18|20",
      "carrier_id": 2089,
      "mvno_match_data": "4D4F",
      "mvno_type": "gid",
      "name": "Public Mobile IMS",
      "protocol": "IPV6",
      "roaming_protocol": "IPV6",
      "types": [
        "ims"
      ],
      "user_visible": false
    },
    {
      "apn": "isp.mb.com",
      "authtype": 0,
      "mvno_match_data": "4D4F",
      "mvno_type": "gid",
      "name": "Tethered Mobile Internet",
      "types": [
        "dun"
      ]
    },
    {
      "apn": "isp.mb.com",
      "carrier_id": 2089,
      "mvno_match_data": "4D4F",
      "mvno_type": "gid",
      "name": "isp.mb.com",
      "protocol": "IP",
      "roaming_protocol": "IP",
      "types": [
        "dun"
      ],
      "user_editable": false
    },
    {
      "apn": "services.mb.com",
      "bearer_bitmask": "1|2|3|9|10|11|13|14|15|18|20",
      "carrier_id": 2089,
      "mvno_match_data": "4D4F",
      "mvno_type": "gid",
      "name": "Public Mobile XCAP",
      "protocol": "IPV6",
      "roaming_protocol": "IPV6",
      "types": [
        "xcap"
      ],
      "user_visible": false
    },
    {
      "apn": "sos",
      "carrier_id": 2089,
      "mvno_match_data": "4D4F",
      "mvno_type": "gid",
      "name": "Public Mobile SOS",
      "protocol": "IPV6",
      "roaming_protocol": "IPV4V6",
      "types": [
        "emergency"
      ],
      "user_visible": false
    },
    {
      "apn": "sp.mb.com",
      "carrier_id": 2089,
      "mmsc": "http://aliasredirect.net/proxy/mb/mmsc",
      "mmsport": 8799,
      "mmsproxy": "mmscproxy.mobility.ca",
      "mvno_match_data": "4D4F",
      "mvno_type": "gid",
      "name": "sp.mb.com",
      "protocol": "IPV4V6",
      "roaming_protocol": "IP",
      "types": [
        "default",
        "fota",
        "hipri",
        "ia",
        "mms",
        "supl"
      ],
      "user_editable": false
    },
    {
      "apn": "sp.mb.com",
      "authtype": 0,
      "mmsc": "http://aliasredirect.net/proxy/mb/mmsc",
      "mmsport": 8799,
      "mmsproxy": "mmscproxy.mobility.ca",
      "mvno_match_data": "4D4F",
      "mvno_type": "gid",
      "name": "Mobile Internet",
      "types": [
        "default",
        "mms",
        "supl"
      ]
    },
    {
      "apn": "isp.mb.com",
      "carrier_id": 10006,
      "mvno_match_data": "5043",
      "mvno_type": "gid",
      "name": "PC Mobile Tethered",
      "types": [
        "dun"
      ],
      "user_editable": false
    },
    {
      "apn": "isp.mb.com",
      "carrier_id": 2053,
      "mvno_match_data": "5043",
      "mvno_type": "gid",
      "name": "Tethered Mobile Internet",
      "protocol": "IP",
      "types": [
        "dun"
      ]
    },
    {
      "apn": "sp.mb.com",
      "carrier_id": 2053,
      "mmsc": "http://aliasredirect.net/proxy/mb/mmsc",
      "mmsport": 8799,
      "mmsproxy": "mmscproxy.mobility.ca",
      "mvno_match_data": "5043",
      "mvno_type": "gid",
      "name": "Mobile Internet",
      "types": [
        "default",
        "ia",
        "mms",
        "supl"
      ]
    },
    {
      "apn": "sp.mb.com",
      "carrier_id": 10006,
      "mmsc": "http://aliasredirect.net/proxy/mb/mmsc",
      "mmsport": 8799,
      "mmsproxy": "mmscproxy.mobility.ca",
      "mvno_match_data": "5043",
      "mvno_type": "gid",
      "name": "PC Mobile",
      "protocol": "IPV4V6",
      "types": [
        "default",
        "ia",
        "mms",
        "supl"
      ],
      "user_editable": false
    },
    {
      "apn": "ims",
      "bearer_bitmask": "3|9|10|11|14|15|18|20",
      "carrier_id": 1404,
      "mvno_match_data": "5455",
      "mvno_type": "gid",
      "name": "TELUS IMS",
      "protocol": "IPV6",
      "roaming_protocol": "IPV6",
      "types": [
        "ims"
      ],
      "user_visible": false
    },
    {
      "apn": "isp.telus.com",
      "authtype": 0,
      "mvno_match_data": "5455",
      "mvno_type": "gid",
      "name": "TELUS ISP",
      "types": [
        "dun"
      ]
    },
    {
      "apn": "isp.telus.com",
      "carrier_id": 1404,
      "mvno_match_data": "5455",
      "mvno_type": "gid",
      "name": "isp.telus.com",
      "protocol": "IP",
      "roaming_protocol": "IP",
      "server": "*",
      "types": [
        "dun"
      ],
      "user_editable": false
    },
    {
      "apn": "services.telus.com",
      "bearer_bitmask": "18",
      "carrier_id": 1404,
      "mmsc": "http://aliasredirect.net/proxy/mmsc",
      "mmsport": 8799,
      "mmsproxy": "mmscproxy.mobility.ca",
      "mvno_match_data": "5455",
      "mvno_type": "gid",
      "name": "TELUS Services",
      "protocol": "IPV6",
      "roaming_protocol": "IPV4V6",
      "types": [
        "mms",
        "xcap"
      ],
      "user_editable": false
    },
    {
      "apn": "services.telus.com",
      "bearer_bitmask": "1|2|3|9|10|11|13|14|15|20",
      "carrier_id": 1404,
      "mvno_match_data": "5455",
      "mvno_type": "gid",
      "name": "TELUS Services",
      "protocol": "IPV6",
      "roaming_protocol": "IPV4V6",
      "types": [
        "xcap"
      ],
      "user_visible": false
    },
    {
      "apn": "services.telus.com",
      "authtype": 0,
      "mtu": 1440,
      "mvno_match_data": "5455",
      "mvno_type": "gid",
      "name": "TELUS Services",
      "protocol": "IPV6",
      "roaming_protocol": "IPV4V6",
      "types": [
        "xcap"
      ]
    },
    {
      "apn": "sos",
      "authtype": 0,
      "mvno_match_data": "5455",
      "mvno_type": "gid",
      "name": "SOS",
      "protocol": "IPV6",
      "roaming_protocol": "IPV4V6",
      "types": [
        "emergency"
      ]
    },
    {
      "apn": "sos",
      "carrier_id": 1404,
      "mvno_match_data": "5455",
      "mvno_type": "gid",
      "name": "TELUS SOS",
      "protocol": "IPV6",
      "roaming_protocol": "IPV4V6",
      "types": [
        "emergency"
      ],
      "user_visible": false
    },
    {
      "apn": "sp.telus.com",
      "bearer_bitmask": "1|2|3|4|5|6|7|8|9|10|11|12|13|14|15|17|20",
      "carrier_id": 1404,
      "mmsc": "http://aliasredirect.net/proxy/mmsc",
      "mmsport": 8799,
      "mmsproxy": "mmscproxy.mobility.ca",
      "mvno_match_data": "5455",
      "mvno_type": "gid",
      "name": "TELUS",
      "protocol": "IPV4V6",
      "roaming_protocol": "IP",
      "types": [
        "default",
        "hipri",
        "ia",
        "mms",
        "supl"
      ],
      "user_editable": false
    },
    {
      "apn": "sp.telus.com",
      "carrier_id": 1404,
      "mmsc": "http://aliasredirect.net/proxy/mmsc",
      "mmsport": 8799,
      "mmsproxy": "mmscproxy.mobility.ca",
      "mvno_match_data": "5455",
      "mvno_type": "gid",
      "name": "TELUS",
      "types": [
        "default",
        "ia",
        "mms",
        "supl"
      ]
    },
    {
      "apn": "sp.telus.com",
      "authtype": 0,
      "mmsc": "http://aliasredirect.net/proxy/mmsc",
      "mmsport": 8799,
      "mmsproxy": "mmscproxy.mobility.ca",
      "mvno_match_data": "5455",
      "mvno_type": "gid",
      "name": "Telus SP",
      "types": [
        "default",
        "mms",
        "supl"
      ]
    }
  ],
  "android_carrier_config": {
    "always_play_remote_hold_tone_bool": true,
    "carrier_default_wfc_ims_enabled_bool": false,
    "carrier_default_wfc_ims_mode_int": 1,
    "carrier_supports_ss_over_ut_bool": true,
    "carrier_volte_available_bool": true,
    "carrier_volte_tty_supported_bool": false,
    "carrier_wfc_ims_available_bool": true,
    "enabledMMS": true,
    "enhanced_4g_lte_on_by_default_bool": true,
    "hide_enhanced_4g_lte_bool": false,
    "maxImageHeight": 1944,
    "maxImageWidth": 2592,
    "maxSubjectLength": 80,
    "rtt_supported_bool": true,
    "smsToMmsTextThreshold": 5
  },
  "capabilities": {
    "esim": "unknown",
    "ims_conference": "unknown",
    "mms": "supported",
    "rcs": "unknown",
    "sms_over_ims": "unknown",
    "video_calling": "unknown",
    "volte": "supported",
    "vonr": "unknown",
    "vowifi": "supported",
    "wifi_calling_roaming": "unknown"
  },
  "display_name": "Carrier 302220",
  "match": {
    "mccmnc": [
      "302220"
    ]
  },
  "profile_id": "open.302220.8f110084f3cf",
  "schema_version": 1
}
