{
  "addons": {
    "emergency_calling": {
      "e911_routing_policy": "auto"
    },
    "network_policy": {
      "network_type_capability": "SPR-XAS-GLB-USA"
    },
    "operator_display": {
      "five_g_icon_branding": "5GAvailable"
    }
  },
  "android_apns": [
    {
      "apn": "ims",
      "name": "SPR Prepaid IMS",
      "protocol": "IPV4V6",
      "types": [
        "ims"
      ]
    },
    {
      "apn": "otasn",
      "name": "SPR Prepaid OTA",
      "protocol": "IPV4V6",
      "types": [
        "default"
      ]
    },
    {
      "apn": "sprpre.pamsn",
      "name": "SPR Prepaid DUN",
      "protocol": "IPV4V6",
      "types": [
        "default"
      ]
    },
    {
      "apn": "x.sprpre.ispsn",
      "mmsc": "https://mmsc.vmobl.com",
      "mmsport": 80,
      "mmsproxy": "oap7.sprintpcs.com",
      "name": "SPR Prepaid Internet",
      "protocol": "IPV4V6",
      "types": [
        "default",
        "mms"
      ]
    }
  ],
  "android_carrier_config": {
    "carrier_volte_available_bool": true
  },
  "capabilities": {
    "esim": "unknown",
    "ims_conference": "unknown",
    "mms": "supported",
    "rcs": "unknown",
    "sms_over_ims": "unknown",
    "video_calling": "unknown",
    "volte": "supported",
    "vonr": "unknown",
    "vowifi": "unknown",
    "wifi_calling_roaming": "unknown"
  },
  "display_name": "SPR Prepaid",
  "match": {
    "mccmnc": [
      "312530"
    ],
    "spn": [
      "SPR Prepaid"
    ]
  },
  "profile_id": "open.312530.16a2e4d5341a",
  "schema_version": 1
}
