{
  "android_apns": [
    {
      "apn": "location.nexteldata.com.mx",
      "name": "Nextel Localizaci\u00f3n",
      "port": 7275,
      "server": "supl.nexteldata.com.mx",
      "types": [
        "supl"
      ]
    },
    {
      "apn": "mms.nexteldata.com.mx",
      "mmsc": "http://3gmms.nexteldata.com.mx",
      "mmsport": 8080,
      "mmsproxy": "129.192.129.104",
      "name": "Nextel MMS",
      "types": [
        "mms"
      ]
    },
    {
      "apn": "modem.nexteldata.com.mx",
      "name": "Nextel Internet",
      "types": [
        "dun"
      ]
    },
    {
      "apn": "wap.nexteldata.com.mx",
      "authtype": 0,
      "name": "Nextel Navegaci\u00f3n",
      "types": [
        "default",
        "supl"
      ]
    }
  ],
  "capabilities": {
    "esim": "unknown",
    "ims_conference": "unknown",
    "mms": "supported",
    "rcs": "unknown",
    "sms_over_ims": "unknown",
    "video_calling": "unknown",
    "volte": "unknown",
    "vonr": "unknown",
    "vowifi": "unknown",
    "wifi_calling_roaming": "unknown"
  },
  "display_name": "Carrier 334090",
  "match": {
    "mccmnc": [
      "334090"
    ]
  },
  "profile_id": "open.334090.d11d8f616ebb",
  "schema_version": 1
}
