{
  "android_apns": [
    {
      "apn": "web",
      "name": "Digicel",
      "types": [
        "default",
        "dun"
      ]
    },
    {
      "apn": "web",
      "name": "Digicel",
      "types": [
        "dun"
      ]
    }
  ],
  "capabilities": {
    "esim": "unknown",
    "ims_conference": "unknown",
    "mms": "unknown",
    "rcs": "unknown",
    "sms_over_ims": "unknown",
    "video_calling": "unknown",
    "volte": "unknown",
    "vonr": "unknown",
    "vowifi": "unknown",
    "wifi_calling_roaming": "unknown"
  },
  "display_name": "Digicel",
  "match": {
    "iccid_prefixes": [
      "890105000843"
    ],
    "mccmnc": [
      "33805"
    ]
  },
  "profile_id": "open.33805.2b7859af9fd9",
  "schema_version": 1
}
