{
  "android_apns": [
    {
      "apn": "airtelgprs.com",
      "name": "Airtel",
      "types": [
        "default",
        "supl"
      ]
    }
  ],
  "capabilities": {
    "esim": "unknown",
    "ims_conference": "unknown",
    "mms": "unknown",
    "rcs": "unknown",
    "sms_over_ims": "unknown",
    "video_calling": "unknown",
    "volte": "unknown",
    "vonr": "unknown",
    "vowifi": "unknown",
    "wifi_calling_roaming": "unknown"
  },
  "display_name": "Airtel",
  "match": {
    "mccmnc": [
      "40402",
      "40403",
      "40406",
      "40410",
      "40428",
      "40431",
      "40437",
      "40440",
      "40441",
      "40442",
      "40445",
      "40449",
      "40470",
      "40490",
      "40492",
      "40493",
      "40495",
      "40496",
      "40497",
      "40498",
      "40551",
      "40552",
      "40554",
      "40556"
    ]
  },
  "profile_id": "open.40402.c47f21a3617a",
  "schema_version": 1
}
