{
  "android_apns": [
    {
      "apn": "mms",
      "carrier_id": 1543,
      "mmsc": "http://10.239.221.47/mms/",
      "mmsport": 8080,
      "mmsproxy": "10.239.221.7",
      "name": "Reliance MMS",
      "protocol": "IPV4V6",
      "roaming_protocol": "IPV4V6",
      "types": [
        "mms"
      ]
    },
    {
      "apn": "mms",
      "mmsc": "http://10.239.221.47/mms/",
      "mmsport": 8080,
      "mmsproxy": "10.239.221.7",
      "name": "Reliance MMS",
      "protocol": "IPV4V6",
      "types": [
        "mms"
      ]
    },
    {
      "apn": "portalnmms",
      "mmsc": "http://mms1.live.vodafone.in/mms/",
      "mmsport": 9401,
      "mmsproxy": "10.10.1.100",
      "name": "Vodafone",
      "port": 9401,
      "proxy": "10.10.1.100",
      "types": [
        "default",
        "mms",
        "supl"
      ]
    },
    {
      "apn": "rcomnet",
      "name": "NetConnect",
      "types": [
        "default",
        "supl"
      ]
    },
    {
      "apn": "rcomwap",
      "name": "Reliance GPRS",
      "port": 8080,
      "proxy": "10.239.221.5",
      "types": [
        "default",
        "supl"
      ]
    },
    {
      "apn": "smartnet",
      "carrier_id": 1543,
      "name": "Reliance Net",
      "protocol": "IPV4V6",
      "roaming_protocol": "IPV4V6",
      "types": [
        "default",
        "ia",
        "supl"
      ]
    },
    {
      "apn": "smartnet",
      "name": "smartnet",
      "protocol": "IPV4V6",
      "types": [
        "default",
        "supl"
      ]
    },
    {
      "apn": "smartnet",
      "name": "Reliance",
      "types": [
        "dun"
      ]
    },
    {
      "apn": "smartwap",
      "authtype": 1,
      "carrier_id": 1543,
      "name": "Reliance WAP",
      "port": 8080,
      "protocol": "IPV4V6",
      "proxy": "10.239.221.7",
      "roaming_protocol": "IPV4V6",
      "types": [
        "default",
        "ia",
        "supl"
      ]
    },
    {
      "apn": "smartwap",
      "authtype": 1,
      "name": "Reliance WAP",
      "port": 8080,
      "protocol": "IPV4V6",
      "proxy": "10.239.221.7",
      "types": [
        "default",
        "supl"
      ]
    }
  ],
  "android_carrier_config": {
    "allow_adding_apns_bool": true,
    "apn_expand_bool": true,
    "auto_retry_failed_wifi_emergency_call": true,
    "carrier_default_wfc_ims_enabled_bool": true,
    "carrier_metered_apn_types_strings": [
      "default",
      "dun",
      "supl",
      "fota"
    ],
    "carrier_metered_roaming_apn_types_strings": [
      "default",
      "dun",
      "supl",
      "fota"
    ],
    "carrier_supports_ss_over_ut_bool": true,
    "carrier_volte_available_bool": true,
    "carrier_volte_provisioned_bool": true,
    "carrier_vt_available_bool": true,
    "carrier_wfc_supports_wifi_only_bool": false,
    "editable_wfc_roaming_mode_bool": true,
    "enabledMMS": true,
    "enhanced_4g_lte_on_by_default_bool": true,
    "hide_enhanced_4g_lte_bool": false,
    "ignore_data_enabled_changed_for_video_calls": true,
    "maxMessageSize": 1048576,
    "recipientLimit": 10,
    "show_apn_setting_cdma_bool": true,
    "support_video_conference_call_bool": true
  },
  "capabilities": {
    "esim": "unknown",
    "ims_conference": "unknown",
    "mms": "supported",
    "rcs": "unknown",
    "sms_over_ims": "unknown",
    "video_calling": "supported",
    "volte": "supported",
    "vonr": "unknown",
    "vowifi": "conditional",
    "wifi_calling_roaming": "unknown"
  },
  "display_name": "Carrier 40467",
  "match": {
    "mccmnc": [
      "40467"
    ]
  },
  "profile_id": "open.40467.01f3eaea37e8",
  "schema_version": 1
}
