{
  "android_apns": [
    {
      "apn": "MB",
      "name": "MultiByte",
      "types": [
        "default",
        "dun"
      ]
    }
  ],
  "capabilities": {
    "esim": "unknown",
    "ims_conference": "unknown",
    "mms": "unknown",
    "rcs": "unknown",
    "sms_over_ims": "unknown",
    "video_calling": "unknown",
    "volte": "unknown",
    "vonr": "unknown",
    "vowifi": "unknown",
    "wifi_calling_roaming": "unknown"
  },
  "display_name": "MultiByte",
  "match": {
    "gid1_prefixes": [
      "58300"
    ],
    "gid2_prefixes": [
      "58301"
    ],
    "mccmnc": [
      "45406"
    ]
  },
  "profile_id": "open.45406.f1b0cf772a4c",
  "schema_version": 1
}
