{
  "android_apns": [
    {
      "apn": "cmhk",
      "mmsc": "http://mms.hk.chinamobile.com/mms",
      "mmsport": 8080,
      "mmsproxy": "172.31.31.36",
      "name": "CMHK",
      "types": [
        "default",
        "mms"
      ]
    },
    {
      "apn": "cmhk",
      "mmsc": "http://mms.hk.chinamobile.com/mms",
      "name": "CMHK",
      "types": [
        "supl"
      ]
    }
  ],
  "android_carrier_config": {
    "carrier_volte_available_bool": true,
    "carrier_vt_available_bool": true,
    "carrier_wfc_ims_available_bool": true,
    "imssms.sms_over_ims_supported_bool": true
  },
  "capabilities": {
    "esim": "unknown",
    "ims_conference": "unknown",
    "mms": "supported",
    "rcs": "unknown",
    "sms_over_ims": "supported",
    "video_calling": "supported",
    "volte": "supported",
    "vonr": "supported",
    "vowifi": "supported",
    "wifi_calling_roaming": "unknown"
  },
  "display_name": "Carrier 45412",
  "match": {
    "mccmnc": [
      "45412"
    ]
  },
  "profile_id": "open.45412.b428d1db6fd5",
  "schema_version": 1
}
