{
  "android_apns": [
    {
      "apn": "default",
      "carrier_id": 741,
      "name": "Cellcom",
      "types": [
        "default",
        "ia",
        "supl"
      ]
    },
    {
      "apn": "default",
      "name": "Cellcom",
      "types": [
        "default",
        "supl"
      ]
    }
  ],
  "capabilities": {
    "esim": "unknown",
    "ims_conference": "unknown",
    "mms": "unknown",
    "rcs": "unknown",
    "sms_over_ims": "unknown",
    "video_calling": "unknown",
    "volte": "unknown",
    "vonr": "unknown",
    "vowifi": "unknown",
    "wifi_calling_roaming": "unknown"
  },
  "display_name": "Carrier 61105",
  "match": {
    "mccmnc": [
      "61105"
    ]
  },
  "profile_id": "open.61105.9c00714bf3cc",
  "schema_version": 1
}
