{
  "android_apns": [
    {
      "apn": "internet",
      "name": "airtel",
      "types": [
        "default",
        "dun"
      ]
    },
    {
      "apn": "internet",
      "name": "airtel",
      "types": [
        "dun"
      ]
    },
    {
      "apn": "web.ug.zain.com",
      "name": "Airtel UG",
      "types": [
        "default",
        "supl"
      ]
    },
    {
      "apn": "web.ug.zain.com",
      "name": "Zain",
      "types": [
        "default",
        "supl"
      ]
    }
  ],
  "capabilities": {
    "esim": "unknown",
    "ims_conference": "unknown",
    "mms": "unknown",
    "rcs": "unknown",
    "sms_over_ims": "unknown",
    "video_calling": "unknown",
    "volte": "unknown",
    "vonr": "unknown",
    "vowifi": "unknown",
    "wifi_calling_roaming": "unknown"
  },
  "display_name": "Zain",
  "match": {
    "mccmnc": [
      "64101"
    ]
  },
  "profile_id": "open.64101.4edf0a12557b",
  "schema_version": 1
}
