{
  "android_apns": [
    {
      "apn": "IMS",
      "carrier_id": 24,
      "name": "Vodacom",
      "protocol": "IPV4V6",
      "types": [
        "ims"
      ]
    },
    {
      "apn": "ims",
      "name": "Vodacom",
      "types": [
        "ims"
      ]
    },
    {
      "apn": "internet",
      "carrier_id": 24,
      "name": "Smart.Vodacom",
      "types": [
        "default",
        "ia",
        "supl"
      ]
    },
    {
      "apn": "internet",
      "name": "internet",
      "types": [
        "dun"
      ]
    },
    {
      "apn": "internet",
      "authtype": 3,
      "name": "internet",
      "port": 8080,
      "proxy": "196.6.128.12",
      "types": [
        "supl"
      ]
    },
    {
      "apn": "iphone.vodacom.za",
      "name": "Vodacom",
      "types": [
        "default",
        "dun"
      ]
    },
    {
      "apn": "lte.vodacom.za",
      "carrier_id": 24,
      "name": "LTE.Vodacom",
      "types": [
        "default",
        "ia",
        "supl"
      ]
    },
    {
      "apn": "lte.vodacom.za",
      "name": "lte.vodacom.za",
      "types": [
        "default",
        "supl"
      ]
    },
    {
      "apn": "lte.vodacom.za",
      "carrier_id": 24,
      "mmsc": "http://mmsc.vodacom4me.co.za",
      "mmsport": 8080,
      "mmsproxy": "196.6.128.13",
      "name": "MMS.Vodacom",
      "types": [
        "mms"
      ]
    },
    {
      "apn": "lte.vodacom.za",
      "mmsc": "http://mmsc.vodacom4me.co.za",
      "mmsport": 8080,
      "mmsproxy": "196.6.128.13",
      "name": "MMS.Vodacom",
      "types": [
        "mms"
      ]
    },
    {
      "apn": "mms.vodacom.net",
      "carrier_id": 24,
      "mmsc": "http://mmsc.vodacom4me.co.za",
      "mmsport": 8080,
      "mmsproxy": "196.6.128.13",
      "name": "MMS.Vodacom",
      "types": [
        "mms"
      ]
    },
    {
      "apn": "xcap",
      "carrier_id": 24,
      "name": "Vodacom",
      "types": [
        "xcap"
      ],
      "user_visible": false
    }
  ],
  "android_carrier_config": {
    "carrier_metered_apn_types_strings": [
      "default",
      "dun",
      "supl"
    ],
    "carrier_volte_available_bool": true,
    "carrier_vt_available_bool": true,
    "carrier_wfc_ims_available_bool": true,
    "editable_enhanced_4g_lte_bool": false,
    "editable_wfc_mode_bool": false,
    "enabledMMS": true,
    "hide_enhanced_4g_lte_bool": true,
    "imssms.sms_over_ims_supported_bool": true,
    "maxMessageSize": 307200,
    "read_only_apn_types_string_array": [
      "*"
    ],
    "smsToMmsTextThreshold": 10
  },
  "capabilities": {
    "esim": "unknown",
    "ims_conference": "unknown",
    "mms": "supported",
    "rcs": "unknown",
    "sms_over_ims": "supported",
    "video_calling": "supported",
    "volte": "supported",
    "vonr": "unknown",
    "vowifi": "supported",
    "wifi_calling_roaming": "unknown"
  },
  "display_name": "Carrier 65501",
  "match": {
    "mccmnc": [
      "65501"
    ]
  },
  "profile_id": "open.65501.e534b996e668",
  "schema_version": 1
}
