{
  "android_apns": [
    {
      "apn": "internet.movistar.sv",
      "authtype": 1,
      "name": "internet.movistar.sv",
      "password": "movistarsv",
      "types": [
        "default",
        "supl"
      ],
      "user": "movistarsv"
    },
    {
      "apn": "mms.movistar.sv",
      "authtype": 1,
      "mmsc": "http://mms.movistar.sv",
      "mmsport": 80,
      "mmsproxy": "10.12.20.1",
      "name": "mms.movistar.sv",
      "password": "movistarsv",
      "types": [
        "mms"
      ],
      "user": "movistarsv"
    }
  ],
  "capabilities": {
    "esim": "unknown",
    "ims_conference": "unknown",
    "mms": "supported",
    "rcs": "unknown",
    "sms_over_ims": "unknown",
    "video_calling": "unknown",
    "volte": "unknown",
    "vonr": "unknown",
    "vowifi": "unknown",
    "wifi_calling_roaming": "unknown"
  },
  "display_name": "Carrier 70604",
  "match": {
    "mccmnc": [
      "70604"
    ]
  },
  "profile_id": "open.70604.a8d516ea497c",
  "schema_version": 1
}
