{
  "android_apns": [
    {
      "apn": "wap.digicelhn.com",
      "authtype": 1,
      "carrier_id": 2248,
      "mmsc": "http://mms.digicelsv.com/servlets/mms",
      "mmsport": 9201,
      "mmsproxy": "172.26.5.12",
      "name": "Honduras:Digicel:Mms:2",
      "types": [
        "mms"
      ]
    },
    {
      "apn": "wap.digicelhn.com",
      "authtype": 1,
      "mmsc": "http://mms.digicelsv.com/servlets/mms",
      "mmsport": 9201,
      "mmsproxy": "172.26.5.12",
      "name": "Honduras:Digicel:Mms:2",
      "types": [
        "mms"
      ]
    },
    {
      "apn": "web.digicelhn.com",
      "authtype": 1,
      "name": "Honduras:Digicel:Internet:2",
      "types": [
        "default"
      ]
    },
    {
      "apn": "web.digicelhn.com",
      "authtype": 1,
      "carrier_id": 2248,
      "name": "Honduras:Digicel:Internet:2",
      "types": [
        "default",
        "ia"
      ]
    }
  ],
  "capabilities": {
    "esim": "unknown",
    "ims_conference": "unknown",
    "mms": "supported",
    "rcs": "unknown",
    "sms_over_ims": "unknown",
    "video_calling": "unknown",
    "volte": "unknown",
    "vonr": "unknown",
    "vowifi": "unknown",
    "wifi_calling_roaming": "unknown"
  },
  "display_name": "Carrier 708040",
  "match": {
    "mccmnc": [
      "708040"
    ]
  },
  "profile_id": "open.708040.7ccf048a55d7",
  "schema_version": 1
}
