{
  "android_apns": [
    {
      "apn": "Wap",
      "mmsc": "http://mmc.digicelpanama.com/servlets/mms",
      "mmsport": 8080,
      "mmsproxy": "172.27.99.99",
      "name": "Digicel",
      "types": [
        "mms"
      ]
    },
    {
      "apn": "wap",
      "mmsc": "http://mmc.digicelpanama.com/servlets/mms",
      "mmsport": 8080,
      "mmsproxy": "172.27.99.99",
      "name": "Digicel MMS",
      "types": [
        "mms"
      ]
    },
    {
      "apn": "wap.digicelpanama.com",
      "carrier_id": 1926,
      "mmsc": "http://mmc.digicelpanama.com/servlets/mms",
      "mmsport": 8080,
      "mmsproxy": "172.27.99.99",
      "name": "MMS",
      "types": [
        "mms"
      ]
    },
    {
      "apn": "wap.digicelpanama.com",
      "mmsc": "http://mmc.digicelpanama.com/servlets/mms",
      "mmsport": 8080,
      "mmsproxy": "172.27.99.99",
      "name": "MMS",
      "types": [
        "mms"
      ]
    },
    {
      "apn": "web",
      "name": "web",
      "types": [
        "default",
        "dun",
        "supl"
      ]
    },
    {
      "apn": "web.digicelpanama.com",
      "carrier_id": 1926,
      "name": "Digicel Internet",
      "types": [
        "default",
        "ia",
        "supl"
      ]
    },
    {
      "apn": "web.digicelpanama.com",
      "name": "web.digicelpanama.com",
      "types": [
        "default",
        "supl"
      ]
    }
  ],
  "android_carrier_config": {
    "enabledMMS": true,
    "maxMessageSize": 2196608,
    "recipientLimit": 10
  },
  "capabilities": {
    "esim": "unknown",
    "ims_conference": "unknown",
    "mms": "supported",
    "rcs": "unknown",
    "sms_over_ims": "unknown",
    "video_calling": "unknown",
    "volte": "unknown",
    "vonr": "unknown",
    "vowifi": "unknown",
    "wifi_calling_roaming": "unknown"
  },
  "display_name": "Carrier 71404",
  "match": {
    "mccmnc": [
      "71404"
    ]
  },
  "profile_id": "open.71404.bda5dfdbe158",
  "schema_version": 1
}
