{
  "addons": {
    "ims": {
      "support_ims_clir_overriding": true
    },
    "network_policy": {
      "display_antenna_limited": true,
      "gcf_sor": true,
      "network_type_capability": "EUR-LTN-GSM-EUR"
    },
    "operator_display": {
      "refer_eons_without_lac": true
    }
  },
  "android_apns": [
    {
      "apn": "ims",
      "name": "IMS VTR CL",
      "protocol": "IPV4V6",
      "roaming_protocol": "IPV4V6",
      "types": [
        "ims"
      ]
    },
    {
      "apn": "movil.vtr.com",
      "name": "Internet",
      "protocol": "IP",
      "roaming_protocol": "IP",
      "types": [
        "default"
      ]
    }
  ],
  "android_carrier_config": {
    "carrier_volte_available_bool": false
  },
  "capabilities": {
    "esim": "unknown",
    "ims_conference": "unknown",
    "mms": "unknown",
    "rcs": "unknown",
    "sms_over_ims": "unsupported",
    "video_calling": "unknown",
    "volte": "unsupported",
    "vonr": "unknown",
    "vowifi": "unknown",
    "wifi_calling_roaming": "unknown"
  },
  "display_name": "VTR",
  "match": {
    "mccmnc": [
      "73008"
    ],
    "spn": [
      "VTR"
    ]
  },
  "profile_id": "open.73008.4ec9739f7a48",
  "schema_version": 1
}
